lm_eval/__init__.py
lm_eval/__main__.py
lm_eval/evaluator.py
lm_eval/utils.py
lm_eval/api/__init__.py
lm_eval/api/filter.py
lm_eval/api/instance.py
lm_eval/api/metrics.py
lm_eval/api/model.py
lm_eval/api/registry.py
lm_eval/api/samplers.py
lm_eval/api/task.py
lm_eval/decontamination/__init__.py
lm_eval/decontamination/archiver.py
lm_eval/decontamination/decontaminate.py
lm_eval/decontamination/janitor.py
lm_eval/filters/__init__.py
lm_eval/filters/decontamination.py
lm_eval/filters/extraction.py
lm_eval/filters/selection.py
lm_eval/filters/transformation.py
lm_eval/models/__init__.py
lm_eval/models/anthropic_llms.py
lm_eval/models/dummy.py
lm_eval/models/gguf.py
lm_eval/models/huggingface.py
lm_eval/models/mamba_lm.py
lm_eval/models/openai_completions.py
lm_eval/models/optimum_lm.py
lm_eval/models/textsynth.py
lm_eval/models/vllm_causallms.py
lm_eval/prompts/__init__.py
lm_eval/tasks/README.md
lm_eval/tasks/__init__.py
lm_eval/tasks/anli/README.md
lm_eval/tasks/anli/anli_r1.yaml
lm_eval/tasks/anli/anli_r2.yaml
lm_eval/tasks/anli/anli_r3.yaml
lm_eval/tasks/arc/README.md
lm_eval/tasks/arc/arc_challenge.yaml
lm_eval/tasks/arc/arc_easy.yaml
lm_eval/tasks/arithmetic/README.md
lm_eval/tasks/arithmetic/arithmetic_1dc.yaml
lm_eval/tasks/arithmetic/arithmetic_2da.yaml
lm_eval/tasks/arithmetic/arithmetic_2dm.yaml
lm_eval/tasks/arithmetic/arithmetic_2ds.yaml
lm_eval/tasks/arithmetic/arithmetic_3da.yaml
lm_eval/tasks/arithmetic/arithmetic_3ds.yaml
lm_eval/tasks/arithmetic/arithmetic_4da.yaml
lm_eval/tasks/arithmetic/arithmetic_4ds.yaml
lm_eval/tasks/arithmetic/arithmetic_5da.yaml
lm_eval/tasks/arithmetic/arithmetic_5ds.yaml
lm_eval/tasks/asdiv/README.md
lm_eval/tasks/asdiv/default.yaml
lm_eval/tasks/babi/README.md
lm_eval/tasks/babi/babi.yaml
lm_eval/tasks/bbh/README.md
lm_eval/tasks/bbh/_generate_configs.py
lm_eval/tasks/bbh/cot_fewshot/_cot_fewshot_template_yaml
lm_eval/tasks/bbh/cot_fewshot/boolean_expressions.yaml
lm_eval/tasks/bbh/cot_fewshot/causal_judgement.yaml
lm_eval-0.4.1.dist-info/LICENSE.md
lm_eval-0.4.1.dist-info/METADATA
lm_eval-0.4.1.dist-info/WHEEL
lm_eval-0.4.1.dist-info/entry_points.txt
lm_eval-0.4.1.dist-info/top_level.txt
lm_eval-0.4.1.dist-info/RECORD
