Metadata-Version: 2.1
Name: lm_eval
Version: 0.4.1
Summary: A framework for evaluating language models
Author-email: EleutherAI <contact@eleuther.ai>
License: MIT
Project-URL: Homepage, https://github.com/EleutherAI/lm-evaluation-harness
Project-URL: Repository, https://github.com/EleutherAI/lm-evaluation-harness
Classifier: Development Status :: 3 - Alpha
Classifier: Programming Language :: Python :: 3
Classifier: License :: OSI Approved :: MIT License
Classifier: Operating System :: OS Independent
Requires-Python: >=3.8
License-File: LICENSE.md
Requires-Dist: accelerate >=0.21.0
Requires-Dist: evaluate
Requires-Dist: datasets >=2.14.0
Requires-Dist: evaluate >=0.4.0
Requires-Dist: jsonlines
Requires-Dist: numexpr
Requires-Dist: peft >=0.2.0
Requires-Dist: pybind11 >=2.6.2
Requires-Dist: pytablewriter
Requires-Dist: rouge-score >=0.0.4
Requires-Dist: sacrebleu >=1.5.0
Requires-Dist: scikit-learn >=0.24.1
Requires-Dist: sqlitedict
Requires-Dist: torch >=1.8
Requires-Dist: tqdm-multiprocess
Requires-Dist: transformers >=4.1
Requires-Dist: zstandard
Provides-Extra: all
Requires-Dist: lm-eval[anthropic] ; extra == 'all'
Requires-Dist: lm-eval[dev] ; extra == 'all'
Requires-Dist: lm-eval[gptq] ; extra == 'all'
Requires-Dist: lm-eval[ifeval] ; extra == 'all'
Requires-Dist: lm-eval[linting] ; extra == 'all'
Requires-Dist: lm-eval[mamba] ; extra == 'all'
Requires-Dist: lm-eval[math] ; extra == 'all'
Requires-Dist: lm-eval[multilingual] ; extra == 'all'
Requires-Dist: lm-eval[openai] ; extra == 'all'
Requires-Dist: lm-eval[promptsource] ; extra == 'all'
Requires-Dist: lm-eval[sentencepiece] ; extra == 'all'
Requires-Dist: lm-eval[testing] ; extra == 'all'
Requires-Dist: lm-eval[vllm] ; extra == 'all'
Requires-Dist: lm-eval[zeno] ; extra == 'all'
Provides-Extra: anthropic
Requires-Dist: anthropic ; extra == 'anthropic'
Provides-Extra: dev
Requires-Dist: pytest ; extra == 'dev'
Requires-Dist: pytest-cov ; extra == 'dev'
Requires-Dist: pytest-xdist ; extra == 'dev'
Requires-Dist: pre-commit ; extra == 'dev'
Requires-Dist: mypy ; extra == 'dev'
Provides-Extra: gptq
Requires-Dist: auto-gptq[triton] >=0.6.0 ; extra == 'gptq'
Provides-Extra: ifeval
Requires-Dist: langdetect ; extra == 'ifeval'
Requires-Dist: immutabledict ; extra == 'ifeval'
Provides-Extra: mamba
Requires-Dist: mamba-ssm ; extra == 'mamba'
Requires-Dist: causal-conv1d ==1.0.2 ; extra == 'mamba'
Provides-Extra: math
Requires-Dist: sympy >=1.12 ; extra == 'math'
Requires-Dist: antlr4-python3-runtime ==4.11 ; extra == 'math'
Provides-Extra: multilingual
Requires-Dist: nagisa >=0.2.7 ; extra == 'multilingual'
Requires-Dist: jieba >=0.42.1 ; extra == 'multilingual'
Requires-Dist: pycountry ; extra == 'multilingual'
Provides-Extra: openai
Requires-Dist: openai ==1.3.9 ; extra == 'openai'
Requires-Dist: tiktoken ; extra == 'openai'
Provides-Extra: optimum
Requires-Dist: optimum[openvino] ; extra == 'optimum'
Provides-Extra: promptsource
Requires-Dist: promptsource >=0.2.3 ; extra == 'promptsource'
Provides-Extra: sentencepiece
Requires-Dist: sentencepiece >=0.1.98 ; extra == 'sentencepiece'
Requires-Dist: protobuf >=4.22.1 ; extra == 'sentencepiece'
Provides-Extra: testing
Requires-Dist: pytest ; extra == 'testing'
Requires-Dist: pytest-cov ; extra == 'testing'
Requires-Dist: pytest-xdist ; extra == 'testing'
Provides-Extra: vllm
Requires-Dist: vllm <=0.2.5 ; extra == 'vllm'
Provides-Extra: zeno
Requires-Dist: pandas ; extra == 'zeno'
Requires-Dist: zeno-client ; extra == 'zeno'
